{
  "$schema": "http://schema.management.azure.com/schemas/2014-04-01-preview/deploymentParameters.json",
  "contentVersion": "1.0.0.0",
  "parameters": {
    "ServerName": {
      "value": "neu-umbraco-mssql-server-cst-prd"
    },
    "AdminLogin": {
      "value": "cst-adminprd"
    },
    "PoolAEdition": {
      "value": "Basic"
    },
    "DBMaxSize": {
      "value": "53687091200"
    },
    "elasticPoolName": {
      "value": "neu-umbraco-mssql-pool-cst-prd"
    },
    "dbName01": {
      "value": "neu-umbraco-db-dbname-cst-prd"
    },
    "dbCollation01": {
      "value": "SQL_Latin1_General_CP1_CI_AS"
    }
  }
}